greet_app/__init__.py
greet_app/main.py
greet_app-0.3.0.dist-info/entry_points.txt
greet_app-0.3.0.dist-info/WHEEL
greet_app-0.3.0.dist-info/METADATA
greet_app-0.3.0.dist-info/RECORD
